[{
	"modelId":3126,
	"modelName":"vivo Y79"
},{
	"modelId":3128,
	"modelName":"vivo Y85"
},{
	"modelId":3129,
	"modelName":"vivo X20"
},{
	"modelId":3130,
	"modelName":"vivo X20 Plus"
},{
	"modelId":3132,
	"modelName":"vivo NEX 旗舰版"
},{
	"modelId":3133,
	"modelName":"vivo X9s"
},{
	"modelId":3134,
	"modelName":"vivo X9s Plus"
},{
	"modelId":3135,
	"modelName":"vivo X9"
},{
	"modelId":3136,
	"modelName":"vivo X9 Plus"
},{
	"modelId":3137,
	"modelName":"vivo X7"
},{
	"modelId":3138,
	"modelName":"vivo X7 Plus"
},{
	"modelId":3139,
	"modelName":"vivo X6s"
},{
	"modelId":3140,
	"modelName":"X6"
},{
	"modelId":3141,
	"modelName":"vivo X6 Plus"
},{
	"modelId":3143,
	"modelName":"vivo X5 Pro"
},{
	"modelId":3144,
	"modelName":"vivo Y67"
},{
	"modelId":3145,
	"modelName":"vivo Y66"
},{
	"modelId":3146,
	"modelName":"vivo Y55"
},{
	"modelId":3147,
	"modelName":"vivo Y53"
},{
	"modelId":3148,
	"modelName":"vivo Y51"
},{
	"modelId":3149,
	"modelName":"vivo Y35"
},{
	"modelId":3150,
	"modelName":"vivo Xplay6"
},{
	"modelId":3151,
	"modelName":"vivo Xplay5"
},{
	"modelId":3153,
	"modelName":"vivo V3"
},{
	"modelId":3154,
	"modelName":"vivo V3 Max"
},{
	"modelId":3155,
	"modelName":"vivo NEX 屏幕指纹版"
},{
	"modelId":3156,
	"modelName":"vivo U3"
},{
	"modelId":3157,
	"modelName":"vivo Y5s"
},{
	"modelId":3158,
	"modelName":"vivo iQOO Neo 855版"
},{
	"modelId":3159,
	"modelName":"vivo S5"
},{
	"modelId":3160,
	"modelName":"vivo Y9s"
},{
	"modelId":3161,
	"modelName":"vivo Y3 标准版"
},{
	"modelId":3162,
	"modelName":"vivo iQOO Neo 855竞速版"
},{
	"modelId":3163,
	"modelName":"vivo X30 (5G)"
},{
	"modelId":3164,
	"modelName":"vivo X30 Pro (5G)"
},{
	"modelId":3165,
	"modelName":"vivo X5M"
},{
	"modelId":3168,
	"modelName":"vivo X9i"
},{
	"modelId":3176,
	"modelName":"vivo X6s Plus"
},{
	"modelId":3187,
	"modelName":"vivo Y37"
},{
	"modelId":3195,
	"modelName":"vivo S7t"
},{
	"modelId":3221,
	"modelName":"vivo S1"
},{
	"modelId":3257,
	"modelName":"vivo Y75"
},{
	"modelId":3259,
	"modelName":"vivo Y66i"
},{
	"modelId":3260,
	"modelName":"vivo Y71"
},{
	"modelId":3261,
	"modelName":"vivo Y83"
},{
	"modelId":3262,
	"modelName":"vivo Y75s"
},{
	"modelId":3263,
	"modelName":"vivo X21i"
},{
	"modelId":3264,
	"modelName":"vivo Z1"
},{
	"modelId":3265,
	"modelName":"vivo Z1i"
},{
	"modelId":3266,
	"modelName":"vivo Y97"
},{
	"modelId":3267,
	"modelName":"vivo X23"
},{
	"modelId":3268,
	"modelName":"vivo Y81s"
},{
	"modelId":3269,
	"modelName":"vivo Z3i"
},{
	"modelId":3270,
	"modelName":"vivo Y73"
},{
	"modelId":3271,
	"modelName":"vivo Z3"
},{
	"modelId":3272,
	"modelName":"vivo Y93"
},{
	"modelId":3273,
	"modelName":"vivo Z1 青春版"
},{
	"modelId":3274,
	"modelName":"vivo X21s"
},{
	"modelId":3275,
	"modelName":"vivo X23 幻彩版"
},{
	"modelId":3276,
	"modelName":"vivo NEX 双屏版"
},{
	"modelId":3277,
	"modelName":"vivo Y69"
},{
	"modelId":3278,
	"modelName":"vivo Y93s"
},{
	"modelId":3279,
	"modelName":"vivo Y89"
},{
	"modelId":3280,
	"modelName":"vivo U1"
},{
	"modelId":3281,
	"modelName":"vivo Y81"
},{
	"modelId":3284,
	"modelName":"vivo iQOO"
},{
	"modelId":3285,
	"modelName":"vivo X27"
},{
	"modelId":3286,
	"modelName":"vivo X27 Pro"
},{
	"modelId":3287,
	"modelName":"vivo Y91"
},{
	"modelId":3288,
	"modelName":"vivo S1 Pro"
},{
	"modelId":3289,
	"modelName":"vivo Z3x"
},{
	"modelId":3290,
	"modelName":"vivo Y3"
},{
	"modelId":3291,
	"modelName":"vivo Z5x"
},{
	"modelId":3292,
	"modelName":"vivo iQOO Neo"
},{
	"modelId":3293,
	"modelName":"vivo Y7s"
},{
	"modelId":3294,
	"modelName":"vivo Z5"
},{
	"modelId":3295,
	"modelName":"vivo iQOO Pro (4G)"
},{
	"modelId":3296,
	"modelName":"vivo iQOO Pro (5G)"
},{
	"modelId":3298,
	"modelName":"vivo NEX 3 (5G)"
},{
	"modelId":3300,
	"modelName":"vivo U3x"
},{
	"modelId":3303,
	"modelName":"vivo Y95"
},{
	"modelId":3304,
	"modelName":"vivo Y71s"
},{
	"modelId":4966,
	"modelName":"vivo Z5i"
},{
	"modelId":7090,
	"modelName":"vivo iQOO 3 (5G)"
},{
	"modelId":7170,
	"modelName":"vivo Z6 (5G)"
},{
	"modelId":7177,
	"modelName":"vivo NEX 3S (5G)"
},{
	"modelId":11710,
	"modelName":"vivo S6 (5G)"
},{
	"modelId":11711,
	"modelName":"vivo Y70"
},{
	"modelId":12054,
	"modelName":"vivo iQOO Neo 3 (5G)"
},{
	"modelId":12055,
	"modelName":"vivo Y50"
},{
	"modelId":13293,
	"modelName":"vivo Z5x 712版"
},{
	"modelId":13312,
	"modelName":"vivo iQOO Z1 (5G)"
},{
	"modelId":13356,
	"modelName":"vivo Y70s (5G)"
},{
	"modelId":13812,
	"modelName":"vivo Y93 标准版"
},{
	"modelId":13821,
	"modelName":"vivo G1 (5G)"
},{
	"modelId":13822,
	"modelName":"vivo X50 (5G)"
},{
	"modelId":13823,
	"modelName":"vivo X50 Pro (5G)"
},{
	"modelId":13921,
	"modelName":"vivo X50 Pro+ (5G)"
},{
	"modelId":13967,
	"modelName":"vivo Y31"
},{
	"modelId":14365,
	"modelName":"vivo Y12"
},{
	"modelId":14426,
	"modelName":"vivo V15"
},{
	"modelId":14427,
	"modelName":"vivo X20 Plus 屏幕指纹版"
},{
	"modelId":14428,
	"modelName":"vivo X21（UD）屏幕指纹版"
},{
	"modelId":14585,
	"modelName":"vivo iQOO Z1x (5G)"
},{
	"modelId":14726,
	"modelName":"vivo iQOO U1"
},{
	"modelId":15546,
	"modelName":"vivo Y51s (5G)"
},{
	"modelId":15742,
	"modelName":"vivo S7 (5G)"
},{
	"modelId":17311,
	"modelName":"vivo iQOO 5 Pro (5G)"
},{
	"modelId":17312,
	"modelName":"vivo iQOO 5 (5G)"
},{
	"modelId":17960,
	"modelName":"vivo NEX"
},{
	"modelId":18895,
	"modelName":"vivo Z3i 标准版"
},{
	"modelId":31434,
	"modelName":"vivo Y73s (5G)"
},{
	"modelId":31571,
	"modelName":"vivo Y30"
},{
	"modelId":31572,
	"modelName":"vivo iQOO U1x"
},{
	"modelId":31746,
	"modelName":"vivo Y3s"
},{
	"modelId":32395,
	"modelName":"vivo S7e (5G)"
},{
	"modelId":35048,
	"modelName":"vivo iQOO U3 (5G)"
},{
	"modelId":35051,
	"modelName":"vivo Y52s (5G)"
},{
	"modelId":35052,
	"modelName":"vivo Y30 标准版"
},{
	"modelId":35063,
	"modelName":"vivo S7e 活力版 (5G)"
},{
	"modelId":35875,
	"modelName":"vivo X60 (5G)"
},{
	"modelId":35876,
	"modelName":"vivo X60 Pro (5G)"
},{
	"modelId":36605,
	"modelName":"vivo Y30 (2021)"
},{
	"modelId":37294,
	"modelName":"vivo iQOO 7 (5G)"
},{
	"modelId":37295,
	"modelName":"vivo Y31s (5G)"
},{
	"modelId":37610,
	"modelName":"vivo X60 Pro+ (5G)"
},{
	"modelId":38328,
	"modelName":"vivo NEX 3 (4G)"
},{
	"modelId":38817,
	"modelName":"vivo X27 8G+128G版"
},{
	"modelId":38927,
	"modelName":"vivo S9e"
},{
	"modelId":38939,
	"modelName":"vivo Y31s 标准版 (5G)"
},{
	"modelId":39459,
	"modelName":"vivo S9 (5G)"
},{
	"modelId":39483,
	"modelName":"vivo Y30g"
},{
	"modelId":39519,
	"modelName":"vivo iQOO Neo 5 (5G)"
},{
	"modelId":40013,
	"modelName":"vivo iQOO U3x"
},{
	"modelId":40134,
	"modelName":"vivo iQOO Z3 (5G)"
},{
	"modelId":40724,
	"modelName":"vivo X60t (5G)"
},{
	"modelId":46485,
	"modelName":"vivo X21"
},{
	"modelId":47663,
	"modelName":"vivo Y52s t1版"
},{
	"modelId":48335,
	"modelName":"vivo Y70t (5G)"
},{
	"modelId":48336,
	"modelName":"vivo iQOO Neo 5 活力版"
},{
	"modelId":48337,
	"modelName":"vivo X60 曲屏版"
},{
	"modelId":49232,
	"modelName":"vivo iQOO U3x 标准版"
},{
	"modelId":49260,
	"modelName":"vivo Y30 活力版"
},{
	"modelId":50020,
	"modelName":"vivo Y53s (5G)"
},{
	"modelId":50226,
	"modelName":"vivo X60t Pro+"
},{
	"modelId":51025,
	"modelName":"vivo Y31s t1版 (5G)"
},{
	"modelId":51178,
	"modelName":"vivo S10 (5G)"
},{
	"modelId":51179,
	"modelName":"vivo S10 Pro (5G)"
},{
	"modelId":52630,
	"modelName":"vivo iQOO 8 (5G)"
},{
	"modelId":52631,
	"modelName":"vivo iQOO 8 Pro (5G)"
},{
	"modelId":52636,
	"modelName":"vivo Y53s t1版 (5G)"
},{
	"modelId":57829,
	"modelName":"vivo Y53s t2版 (5G)"
},{
	"modelId":58515,
	"modelName":"vivo X70 (5G)"
},{
	"modelId":58516,
	"modelName":"vivo X70 Pro (5G)"
},{
	"modelId":58517,
	"modelName":"vivo X70 Pro+ (5G)"
},{
	"modelId":58754,
	"modelName":"vivo Y12s"
},{
	"modelId":58862,
	"modelName":"vivo iQOO Z5 (5G)"
},{
	"modelId":78602,
	"modelName":"vivo S10e"
},{
	"modelId":78603,
	"modelName":"vivo T1"
},{
	"modelId":78604,
	"modelName":"vivo T1x"
},{
	"modelId":78852,
	"modelName":"vivo iQOO Z5x (5G)"
},{
	"modelId":81230,
	"modelName":"vivo Y71t"
},{
	"modelId":83691,
	"modelName":"vivo Y76S"
},{
	"modelId":84493,
	"modelName":"vivo Y74s"
},{
	"modelId":84506,
	"modelName":"vivo Y31s t2版 (5G)"
},{
	"modelId":84678,
	"modelName":"vivo Y54s"
},{
	"modelId":84732,
	"modelName":"vivo Y55s (5G)"
},{
	"modelId":84815,
	"modelName":"vivo X70t"
},{
	"modelId":85872,
	"modelName":"vivo Y50t"
},{
	"modelId":86657,
	"modelName":"vivo iQOO Neo 5S (5G)"
},{
	"modelId":86658,
	"modelName":"vivo iQOO Neo 5 SE (5G)"
},{
	"modelId":86676,
	"modelName":"vivo S12 (5G)"
},{
	"modelId":86677,
	"modelName":"vivo S12 Pro (5G)"
},{
	"modelId":86801,
	"modelName":"vivo iQOO U5 (5G)"
},{
	"modelId":87433,
	"modelName":"vivo iQOO 9 (5G)"
},{
	"modelId":87441,
	"modelName":"vivo iQOO 9 Pro (5G)"
},{
	"modelId":87943,
	"modelName":"vivo Y33s"
},{
	"modelId":88184,
	"modelName":"vivo Y32"
},{
	"modelId":88284,
	"modelName":"vivo Y10 t1版"
},{
	"modelId":88574,
	"modelName":"vivo Y10"
},{
	"modelId":89077,
	"modelName":"vivo Y33s (5G)"
},{
	"modelId":89250,
	"modelName":"vivo iQOO U5x"
},{
	"modelId":89795,
	"modelName":"vivo X Fold"
},{
	"modelId":89796,
	"modelName":"vivo X Note"
},{
	"modelId":89854,
	"modelName":"vivo iQOO Neo 6 (5G)"
},{
	"modelId":90406,
	"modelName":"vivo Y53s NFC (5G)"
},{
	"modelId":90575,
	"modelName":"vivo X80"
},{
	"modelId":90584,
	"modelName":"vivo X80 Pro"
},{
	"modelId":90826,
	"modelName":"vivo S15e"
},{
	"modelId":90859,
	"modelName":"vivo X80 Pro 天玑版 (5G)"
},{
	"modelId":90860,
	"modelName":"vivo iQOO Neo 6 SE (5G)"
},{
	"modelId":91449,
	"modelName":"vivo S15"
},{
	"modelId":91450,
	"modelName":"vivo S15 Pro"
},{
	"modelId":92771,
	"modelName":"vivo Y33e"
},{
	"modelId":93194,
	"modelName":"vivo T2x"
},{
	"modelId":93195,
	"modelName":"vivo Y72t"
},{
	"modelId":94386,
	"modelName":"vivo Y77"
},{
	"modelId":94524,
	"modelName":"vivo iQOO 10 (5G)"
},{
	"modelId":94525,
	"modelName":"vivo iQOO 10 Pro (5G)"
},{
	"modelId":94564,
	"modelName":"vivo Y10 t2版"
},{
	"modelId":94591,
	"modelName":"vivo iQOO U5e"
},{
	"modelId":94926,
	"modelName":"vivo Y32t"
},{
	"modelId":95170,
	"modelName":"vivo Y77e"
},{
	"modelId":95172,
	"modelName":"vivo Y77e t1版"
},{
	"modelId":95352,
	"modelName":"vivo iQOO Z6 (5G)"
},{
	"modelId":95353,
	"modelName":"vivo iQOO Z6x (5G)"
},{
	"modelId":96131,
	"modelName":"vivo X Fold+"
},{
	"modelId":96927,
	"modelName":"vivo Y52t"
},{
	"modelId":97116,
	"modelName":"vivo Y73t"
},{
	"modelId":97364,
	"modelName":"vivo Y75s (5G)"
},{
	"modelId":97365,
	"modelName":"vivo iQOO Neo 7 (5G)"
},{
	"modelId":99050,
	"modelName":"vivo X90"
},{
	"modelId":99051,
	"modelName":"vivo X90 Pro"
},{
	"modelId":99052,
	"modelName":"vivo X90 Pro+"
},{
	"modelId":99781,
	"modelName":"vivo iQOO 11 (5G)"
},{
	"modelId":99782,
	"modelName":"vivo iQOO Neo 7 SE (5G)"
},{
	"modelId":99991,
	"modelName":"vivo Y35 (5G)"
},{
	"modelId":99992,
	"modelName":"vivo iQOO 11 Pro (5G)"
},{
	"modelId":100428,
	"modelName":"vivo S16"
},{
	"modelId":100433,
	"modelName":"vivo S16 Pro"
},{
	"modelId":100436,
	"modelName":"vivo S16e"
},{
	"modelId":100761,
	"modelName":"vivo iQOO Neo 7 竞速版 (5G)"
},{
	"modelId":101565,
	"modelName":"vivo Y35m"
}]